PyDL7-0.0.3.dist-info/DESCRIPTION.rst
PyDL7-0.0.3.dist-info/METADATA
PyDL7-0.0.3.dist-info/RECORD
PyDL7-0.0.3.dist-info/WHEEL
PyDL7-0.0.3.dist-info/entry_points.txt
PyDL7-0.0.3.dist-info/metadata.json
PyDL7-0.0.3.dist-info/top_level.txt
divelog/__init__.py
divelog/command_line.py
divelog/files.py
dl7/__init__.py
dljson/__init__.py
uddf/__init__.py
