Metadata-Version: 2.0
Name: PyDL7
Version: 0.0.3
Summary: Python API for parsing DAN Dive Log files.
Home-page: https://github.com/johnstonskj/PyDL7
Author: Simon Johnston
Author-email: johnstonskj@gmail.com
License: MIT
Download-URL: https://pypi.python.org/pypi/PyDL7
Platform: UNKNOWN
Classifier: Development Status :: 3 - Alpha
Classifier: Intended Audience :: Developers
Classifier: License :: OSI Approved :: MIT License
